maze/__init__.py
maze/adsorbate.py
maze/cif_download.py
maze/extra_framework_maker.py
maze/index_mapper.py
maze/io_zeolite.py
maze/perfect_zeolite.py
maze/silanol.py
maze/zeolite.py
maze/zeolite_db.py
MAZE_sim-0.1.1.dist-info/LICENSE.txt
MAZE_sim-0.1.1.dist-info/METADATA
MAZE_sim-0.1.1.dist-info/WHEEL
MAZE_sim-0.1.1.dist-info/top_level.txt
MAZE_sim-0.1.1.dist-info/RECORD
